oqs/__init__.py
oqs/oqs.py
oqs/rand.py
liboqs_python-0.14.0.dist-info/METADATA
liboqs_python-0.14.0.dist-info/WHEEL
liboqs_python-0.14.0.dist-info/licenses/LICENSE.txt
liboqs_python-0.14.0.dist-info/RECORD
