Metadata-Version: 2.4
Name: liboqs-python
Version: 0.14.0
Summary: Python bindings for liboqs, providing post-quantum public key cryptography algorithms
Project-URL: homepage, https://github.com/open-quantum-safe/liboqs-python
Project-URL: repository, https://github.com/open-quantum-safe/liboqs-python.git
Author-email: Open Quantum Safe project <contact@openquantumsafe.org>
License: MIT License
License-File: LICENSE.txt
Requires-Python: >=3.9
Provides-Extra: dev
Requires-Dist: isort==5.13.2; extra == 'dev'
Requires-Dist: nose2==0.15.1; extra == 'dev'
Requires-Dist: pre-commit==4.1.0; extra == 'dev'
Requires-Dist: ruff==0.9.4; extra == 'dev'
Provides-Extra: lint
Requires-Dist: mypy==1.14.1; extra == 'lint'
Requires-Dist: types-pytz==2024.2.0.20241221; extra == 'lint'
